{"name":"Gol","tagline":"Go library: cache, cookie, counter, error, fastbuf, filepath, genid, hash, jsonConfig, reflection, session, test, tplEngin/i18n/plural","body":"### About GoL\r\nGo Library (GoL) - набор пакетов языка программирования Go    \r\nunder terms of ISC license\r\n\r\n### cashe\r\nПакет представляет собой реализацию потокобезопасной хеш таблицы типа `map[string]interface{}` котрая и является in-memory хранилищем кеша.\r\n\r\n```\r\ncashe.New(\r\n\thash func([]byte) uint32,   // хеш функция\r\n\tinit_bucketscount int,      // первоначальное ко-во элементов таблицы\r\n\tifreadthenlive bool,        // продлевать время жизни элемента при обращении к нему\r\n\tduration time.Duration,     // гарантированное время жизни элемента\r\n\tcallback func(key *string, val *interface{}) // функция выполняемая при удалении элемента по причине истечения срока его жизни в кеше\r\n) Cache\r\n```\r\nсоздаваемый объект реализует интерфейс:\r\n```\r\nCache interface {                 \r\n\t\tGetBucketsStat() (countitem uint64, countbucket uint32, stat [][2]int) // получить информацию по структуре кеша(кол-во бакетов) и статистику распределения записей.\r\n\t\tGet(string) interface{}          // получить запись\r\n\t\tSet(string, interface{}) bool    // записать в кеш\r\n\t\tDel(string) (val interface{})    // удалить из кеша\r\n\t\tInc(string, float64) interface{} // инкремент/декремент значения  \r\n\t\tSave(io.Writer) error            // сохранить в писателя\r\n\t\tSaveFile(string) error           // сохранить в файл \r\n\t\tLoad(io.Reader) error            // загрузить из читателя\r\n\t\tLoadFile(string) error           // загрузить из файла\r\n\t\tLen() I_counter                  // объект реализующий счётчик для возможного лимитирования кол-ва принимаемых записей\r\n\t}\r\n```\r\nобъект счётчика реализует интерфейс:\r\n```\r\nI_counter interface {\r\n\t\tGet() uint64\r\n\t\tGetLimit() uint64\r\n\t\tSetLimit(v uint64)\r\n\t\tCheck() bool\r\n\t}\r\n```\r\nреализацией данного интерфейса является пакет `counter`\r\n\r\n### hash\r\nПакет является коллекцией быстрых некриптографических хеш функций используемых в пакете `cashe`\r\n\r\n### err\r\nПакет предоставляет реализацию объекта интерфейса `error` который обладает публичным свойством текста ошибки что позволяет редактировать текст сообщения уже сгенерированной ошибки. \r\n```\r\n// editable error struct\r\ntype OpenErr struct {\r\n\tText string\r\n\tCode int\r\n}\r\n```\r\nИ удобную функцию, синтаксический сахар, генерации исключения на основе ошибки.\r\n```\r\nfunc Panic(e error)\r\n```\r\n\r\n","google":"","note":"Don't delete this file! It's used internally to help with page regeneration."}